github_actions_test/__init__.py
github_actions_test/__version__.py
github_actions_test/cli.py
github_actions_test/const.py
github_actions_test/exceptions.py
github_actions_test/hello.py
github_actions_test-0.2.0.dist-info/entry_points.txt
github_actions_test-0.2.0.dist-info/LICENSE
github_actions_test-0.2.0.dist-info/WHEEL
github_actions_test-0.2.0.dist-info/METADATA
github_actions_test-0.2.0.dist-info/RECORD
