Metadata-Version: 2.1
Name: github-actions-test
Version: 0.2.0
Summary: Project to test Github Actions
Home-page: https://github.com/esciara/github_actions_test
License: MIT
Keywords: github_actions_test
Author: Emmanuel Sciara
Author-email: emmanuel.sciara@gmail.com
Requires-Python: >=3.6,<4.0
Classifier: Development Status :: 2 - Pre-Alpha
Classifier: Intended Audience :: Developers
Classifier: License :: OSI Approved :: MIT License
Classifier: Natural Language :: English
Classifier: Programming Language :: Python :: 3
Classifier: Programming Language :: Python :: 3.6
Classifier: Programming Language :: Python :: 3.7
Classifier: Programming Language :: Python :: 3.8
Provides-Extra: bdd
Provides-Extra: docs
Provides-Extra: format
Provides-Extra: lint
Provides-Extra: repl
Provides-Extra: test
Provides-Extra: type
Requires-Dist: PyHamcrest (>=1.9,<2.0); extra == "test" or extra == "bdd"
Requires-Dist: behave (>=1.2,<2.0); extra == "bdd"
Requires-Dist: black; extra == "format"
Requires-Dist: bpython (>=0.18,<0.19); extra == "repl"
Requires-Dist: cleo (>=0.7.6,<0.8.0)
Requires-Dist: flake8 (>=3.7,<4.0); extra == "lint"
Requires-Dist: flake8-bugbear (>=19.8.0,<20.0.0); extra == "lint"
Requires-Dist: isort (>=4.3,<5.0); extra == "format"
Requires-Dist: mypy (>=0.740.0,<0.741.0); extra == "type"
Requires-Dist: pydocstyle (>=3.0,<4.0); extra == "lint"
Requires-Dist: pylint (>=2.3,<3.0); extra == "lint"
Requires-Dist: pytest (>=5.1,<6.0); extra == "test"
Requires-Dist: pytest-asyncio (>=0.10.0,<0.11.0); extra == "test"
Requires-Dist: pytest-cov (>=2.8.1,<3.0.0); extra == "test"
Requires-Dist: pytest-html (>=2.0.1,<3.0.0); extra == "test"
Requires-Dist: pytest-mock (>=1.13.0,<2.0.0); extra == "test"
Requires-Dist: seed-isort-config (>=1.9.3,<2.0.0); extra == "format"
Requires-Dist: sphinx (>=2.3.0,<3.0.0); extra == "docs"
Requires-Dist: sphinx-autobuild (>=0.7.1,<0.8.0); extra == "docs"
Requires-Dist: sphinx-autodoc-typehints (>=1.10.3,<2.0.0); extra == "docs"
Requires-Dist: sphinx_rtd_theme (>=0.4.3,<0.5.0); extra == "docs"
Requires-Dist: yapf (>=0.27.0,<0.28.0); extra == "lint"
